certifi_linux.pth
certifi_linux/__about__.py
certifi_linux/__init__.py
certifi_linux/certifi_linux.py
certifi_linux/patch_certifi.py
certifi_linux-1.1.0.dist-info/METADATA
certifi_linux-1.1.0.dist-info/WHEEL
certifi_linux-1.1.0.dist-info/licenses/LICENSE.txt
certifi_linux-1.1.0.dist-info/RECORD
