Metadata-Version: 2.4
Name: certifi-linux
Version: 1.1.0
Summary: Certifi patch for using Linux cert trust stores
Project-URL: Changelog, https://github.com/m-birke/certifi-linux/blob/main/CHANGELOG.md
Project-URL: Documentation, https://github.com/m-birke/certifi-linux#readme
Project-URL: Homepage, https://github.com/m-birke/certifi-linux
Project-URL: Issue, https://github.com/m-birke/certifi-linux/issues
Project-URL: Source, https://github.com/m-birke/certifi-linux
Author-email: Birkenbach Marius <wesci@web.de>
License-File: LICENSE.txt
Keywords: certifi,certificates,certs,linux,requests,ssl,tls
Classifier: Development Status :: 5 - Production/Stable
Classifier: License :: OSI Approved :: MIT License
Classifier: Operating System :: POSIX :: Linux
Classifier: Programming Language :: Python
Classifier: Programming Language :: Python :: 3.7
Classifier: Programming Language :: Python :: 3.8
Classifier: Programming Language :: Python :: 3.9
Classifier: Programming Language :: Python :: 3.10
Classifier: Programming Language :: Python :: 3.11
Classifier: Programming Language :: Python :: 3.12
Classifier: Programming Language :: Python :: 3.13
Classifier: Programming Language :: Python :: Implementation :: CPython
Requires-Python: >=3.7
Requires-Dist: wrapt
